{
  "name": "@subsquid/substrate-processor",
  "entries": [
    {
      "version": "0.3.0",
      "tag": "@subsquid/substrate-processor_v0.3.0",
      "date": "Mon, 07 Feb 2022 15:16:41 GMT",
      "comments": {
        "patch": [
          {
            "comment": "handle camelCase call names within `ctx._chain.decodeCall()`"
          },
          {
            "comment": "handle tx serialization failures"
          }
        ],
        "minor": [
          {
            "comment": "allow to customize transaction isolation level"
          }
        ],
        "dependency": [
          {
            "comment": "Updating dependency \"@subsquid/scale-codec-json\" from `^0.1.0` to `^0.1.1`"
          },
          {
            "comment": "Updating dependency \"@subsquid/substrate-metadata\" from `^0.2.0` to `^0.3.0`"
          }
        ]
      }
    },
    {
      "version": "0.2.6",
      "tag": "@subsquid/substrate-processor_v0.2.6",
      "date": "Wed, 02 Feb 2022 11:01:32 GMT",
      "comments": {
        "patch": [
          {
            "comment": "upgrade dependencies"
          }
        ],
        "dependency": [
          {
            "comment": "Updating dependency \"@subsquid/rpc-client\" from `^0.1.2` to `^0.1.3`"
          },
          {
            "comment": "Updating dependency \"@subsquid/scale-codec-json\" from `^0.0.5` to `^0.1.0`"
          },
          {
            "comment": "Updating dependency \"@subsquid/substrate-metadata\" from `^0.1.3` to `^0.2.0`"
          },
          {
            "comment": "Updating dependency \"@subsquid/typeorm-config\" from `^0.0.3` to `^0.0.4`"
          },
          {
            "comment": "Updating dependency \"@subsquid/util\" from `^0.0.3` to `^0.0.4`"
          }
        ]
      }
    },
    {
      "version": "0.2.5",
      "tag": "@subsquid/substrate-processor_v0.2.5",
      "date": "Wed, 26 Jan 2022 13:21:07 GMT",
      "comments": {
        "patch": [
          {
            "comment": "prevent quadratic sizes of fetched data"
          },
          {
            "comment": "fix graphql error handling"
          }
        ]
      }
    },
    {
      "version": "0.2.4",
      "tag": "@subsquid/substrate-processor_v0.2.4",
      "date": "Tue, 25 Jan 2022 12:44:12 GMT",
      "comments": {
        "patch": [
          {
            "comment": "fix fetching of extrinsics with underscore in the name"
          }
        ]
      }
    },
    {
      "version": "0.2.3",
      "tag": "@subsquid/substrate-processor_v0.2.3",
      "date": "Thu, 20 Jan 2022 08:42:53 GMT",
      "comments": {
        "patch": [
          {
            "comment": "include src files into npm package"
          }
        ],
        "dependency": [
          {
            "comment": "Updating dependency \"@subsquid/rpc-client\" from `^0.1.1` to `^0.1.2`"
          },
          {
            "comment": "Updating dependency \"@subsquid/scale-codec-json\" from `^0.0.4` to `^0.0.5`"
          },
          {
            "comment": "Updating dependency \"@subsquid/substrate-metadata\" from `^0.1.1` to `^0.1.2`"
          },
          {
            "comment": "Updating dependency \"@subsquid/typeorm-config\" from `^0.0.2` to `^0.0.3`"
          },
          {
            "comment": "Updating dependency \"@subsquid/util\" from `^0.0.2` to `^0.0.3`"
          }
        ]
      }
    },
    {
      "version": "0.2.2",
      "tag": "@subsquid/substrate-processor_v0.2.2",
      "date": "Tue, 18 Jan 2022 09:31:27 GMT",
      "comments": {
        "patch": [
          {
            "comment": "change license to GPL3"
          }
        ],
        "dependency": [
          {
            "comment": "Updating dependency \"@subsquid/rpc-client\" from `^0.1.0` to `^0.1.1`"
          },
          {
            "comment": "Updating dependency \"@subsquid/scale-codec-json\" from `^0.0.3` to `^0.0.4`"
          },
          {
            "comment": "Updating dependency \"@subsquid/substrate-metadata\" from `^0.1.0` to `^0.1.1`"
          },
          {
            "comment": "Updating dependency \"@subsquid/typeorm-config\" from `^0.0.1` to `^0.0.2`"
          },
          {
            "comment": "Updating dependency \"@subsquid/util\" from `^0.0.1` to `^0.0.2`"
          }
        ]
      }
    },
    {
      "version": "0.2.1",
      "tag": "@subsquid/substrate-processor_v0.2.1",
      "date": "Sun, 16 Jan 2022 18:13:02 GMT",
      "comments": {
        "none": [
          {
            "comment": "dev deps: upgrade `expect`"
          }
        ],
        "dependency": [
          {
            "comment": "Updating dependency \"@subsquid/scale-codec-json\" from `^0.0.2` to `^0.0.3`"
          }
        ]
      }
    },
    {
      "version": "0.2.0",
      "tag": "@subsquid/substrate-processor_v0.2.0",
      "date": "Thu, 13 Jan 2022 16:05:36 GMT",
      "comments": {
        "minor": [
          {
            "comment": "Provide event.extrinsicId in the block header"
          }
        ],
        "patch": [
          {
            "comment": "Fix decoding errors for variant types (when using typegen classes)"
          }
        ],
        "dependency": [
          {
            "comment": "Updating dependency \"@subsquid/rpc-client\" from `^0.0.2` to `^0.1.0`"
          },
          {
            "comment": "Updating dependency \"@subsquid/scale-codec-json\" from `^0.0.1` to `^0.0.2`"
          },
          {
            "comment": "Updating dependency \"@subsquid/substrate-metadata\" from `^0.0.2` to `^0.1.0`"
          }
        ]
      }
    },
    {
      "version": "0.1.1",
      "tag": "@subsquid/substrate-processor_v0.1.1",
      "date": "Mon, 10 Jan 2022 17:09:28 GMT",
      "comments": {
        "patch": [
          {
            "comment": "use new `@subsquid/scale-codec-json` for archive data"
          }
        ],
        "dependency": [
          {
            "comment": "Updating dependency \"@subsquid/scale-codec-json\" from `^0.0.0` to `^0.0.1`"
          },
          {
            "comment": "Updating dependency \"@subsquid/substrate-metadata\" from `^0.0.1` to `^0.0.2`"
          }
        ]
      }
    },
    {
      "version": "0.1.0",
      "tag": "@subsquid/substrate-processor_v0.1.0",
      "date": "Sat, 08 Jan 2022 13:00:12 GMT",
      "comments": {
        "patch": [
          {
            "comment": "fix possibility of double ingestion"
          },
          {
            "comment": "recover from chain connection losses"
          }
        ],
        "minor": [
          {
            "comment": "rename metric: `substrate_processor:last_processed_block` to `sqd_processor_last_block`"
          },
          {
            "comment": "rename metric: `substrate_processor:chain_height` to `sqd_processor_chain_height`"
          },
          {
            "comment": "add metric: `sqd_processor_mapping_blocks_per_second`"
          },
          {
            "comment": "add metric: `sqd_processor_ingest_blocks_per_second`"
          },
          {
            "comment": "add metric: `sqd_processor_sync_eta_seconds`"
          },
          {
            "comment": "add metric: `sqd_processor_sync_ratio`"
          }
        ],
        "dependency": [
          {
            "comment": "Updating dependency \"@subsquid/rpc-client\" from `^0.0.1` to `^0.0.2`"
          }
        ]
      }
    },
    {
      "version": "0.0.1",
      "tag": "@subsquid/substrate-processor_v0.0.1",
      "date": "Mon, 03 Jan 2022 16:07:32 GMT",
      "comments": {
        "patch": [
          {
            "comment": "set `publishConfig.access` to `public`"
          }
        ],
        "dependency": [
          {
            "comment": "Updating dependency \"@subsquid/rpc-client\" from `^0.0.0` to `^0.0.1`"
          },
          {
            "comment": "Updating dependency \"@subsquid/scale-codec\" from `^0.0.0` to `^0.0.1`"
          },
          {
            "comment": "Updating dependency \"@subsquid/substrate-metadata\" from `^0.0.0` to `^0.0.1`"
          },
          {
            "comment": "Updating dependency \"@subsquid/typeorm-config\" from `^0.0.0` to `^0.0.1`"
          },
          {
            "comment": "Updating dependency \"@subsquid/util\" from `^0.0.0` to `^0.0.1`"
          }
        ]
      }
    },
    {
      "version": "0.0.0",
      "tag": "@subsquid/substrate-processor_v0.0.0",
      "date": "Mon, 03 Jan 2022 12:24:26 GMT",
      "comments": {}
    }
  ]
}
