{
  "name": "@subsquid/typeorm-config",
  "entries": [
    {
      "version": "1.1.0",
      "tag": "@subsquid/typeorm-config_v1.1.0",
      "date": "Fri, 24 Jun 2022 22:07:05 GMT",
      "comments": {
        "patch": [
          {
            "comment": "upgrade dependencies"
          }
        ],
        "minor": [
          {
            "comment": "typeorm upgrade from `0.2.x` to `0.3.6`"
          }
        ],
        "dependency": [
          {
            "comment": "Updating dependency \"@subsquid/util-naming\" from `^0.0.0` to `^0.0.1`"
          }
        ]
      }
    },
    {
      "version": "1.0.0",
      "tag": "@subsquid/typeorm-config_v1.0.0",
      "date": "Sun, 19 Jun 2022 21:26:31 GMT",
      "comments": {
        "major": [
          {
            "comment": "Introduce FireSquid"
          }
        ]
      }
    },
    {
      "version": "0.0.5",
      "tag": "@subsquid/typeorm-config_v0.0.5",
      "date": "Wed, 20 Apr 2022 22:55:27 GMT",
      "comments": {
        "dependency": [
          {
            "comment": "Updating dependency \"@subsquid/util\" from `^0.0.4` to `^0.0.5`"
          }
        ]
      }
    },
    {
      "version": "0.0.4",
      "tag": "@subsquid/typeorm-config_v0.0.4",
      "date": "Wed, 02 Feb 2022 11:01:32 GMT",
      "comments": {
        "patch": [
          {
            "comment": "upgrade dependencies"
          }
        ],
        "dependency": [
          {
            "comment": "Updating dependency \"@subsquid/util\" from `^0.0.3` to `^0.0.4`"
          }
        ]
      }
    },
    {
      "version": "0.0.3",
      "tag": "@subsquid/typeorm-config_v0.0.3",
      "date": "Thu, 20 Jan 2022 08:42:53 GMT",
      "comments": {
        "patch": [
          {
            "comment": "include src files into npm package"
          }
        ],
        "dependency": [
          {
            "comment": "Updating dependency \"@subsquid/util\" from `^0.0.2` to `^0.0.3`"
          }
        ]
      }
    },
    {
      "version": "0.0.2",
      "tag": "@subsquid/typeorm-config_v0.0.2",
      "date": "Tue, 18 Jan 2022 09:31:27 GMT",
      "comments": {
        "patch": [
          {
            "comment": "change license to GPL3"
          }
        ],
        "dependency": [
          {
            "comment": "Updating dependency \"@subsquid/util\" from `^0.0.1` to `^0.0.2`"
          }
        ]
      }
    },
    {
      "version": "0.0.1",
      "tag": "@subsquid/typeorm-config_v0.0.1",
      "date": "Mon, 03 Jan 2022 16:07:32 GMT",
      "comments": {
        "patch": [
          {
            "comment": "set `publishConfig.access` to `public`"
          }
        ],
        "dependency": [
          {
            "comment": "Updating dependency \"@subsquid/util\" from `^0.0.0` to `^0.0.1`"
          }
        ]
      }
    },
    {
      "version": "0.0.0",
      "tag": "@subsquid/typeorm-config_v0.0.0",
      "date": "Mon, 03 Jan 2022 12:24:26 GMT",
      "comments": {}
    }
  ]
}
